MANIFEST.in
README.rst
requirements.txt
setup.cfg
setup.py
djmicrosip_comparadb/__init__.py
djmicrosip_comparadb/__init__.pyc
djmicrosip_comparadb/config.pyc
djmicrosip_comparadb/forms.pyc
djmicrosip_comparadb/models.pyc
djmicrosip_comparadb/urls.pyc
djmicrosip_comparadb/views.pyc
djmicrosip_comparadb.egg-info/PKG-INFO
djmicrosip_comparadb.egg-info/SOURCES.txt
djmicrosip_comparadb.egg-info/dependency_links.txt
djmicrosip_comparadb.egg-info/requires.txt
djmicrosip_comparadb.egg-info/top_level.txt
djmicrosip_comparadb/static/djmicrosip_comparadb/js/compara_db.js
djmicrosip_comparadb/templates/djmicrosip_comparadb/articulos.html
djmicrosip_comparadb/templates/djmicrosip_comparadb/articulos2.html
djmicrosip_comparadb/templates/djmicrosip_comparadb/articulosrenombrar.html
djmicrosip_comparadb/templates/djmicrosip_comparadb/base.html
djmicrosip_comparadb/templates/djmicrosip_comparadb/costos.html
djmicrosip_comparadb/templates/djmicrosip_comparadb/costosprom.html
djmicrosip_comparadb/templates/djmicrosip_comparadb/index.html
djmicrosip_comparadb/templates/djmicrosip_comparadb/localizaciones.html
djmicrosip_comparadb/templates/djmicrosip_comparadb/precios_linea.html